Metadata-Version: 2.4
Name: mseep-twist-mcp-server
Version: 0.1.1
Summary: A Twist MCP server written in Python
Author-email: mseep <support@skydeck.ai>
License-Expression: MIT
Requires-Python: >=3.10
License-File: LICENSE
Requires-Dist: mcp[cli]>=1.6.0
Requires-Dist: requests>=2.30.0
Dynamic: license-file
